qwen3_coder/__init__.py
qwen3_coder/__main__.py
qwen3_coder/api_client.py
qwen3_coder/cli.py
qwen3_coder/config.py
qwen3_coder/context_manager.py
qwen3_coder/exceptions.py
qwen3_coder/rate_limiter.py
qwen3_coder/session.py
qwen3_coder/terminal.py
qwen3_coder/token_manager.py
qwen3_coder/token_utils.py
qwen3_coder_agent-0.1.1.dist-info/LICENSE
qwen3_coder_agent-0.1.1.dist-info/METADATA
qwen3_coder_agent-0.1.1.dist-info/WHEEL
qwen3_coder_agent-0.1.1.dist-info/entry_points.txt
qwen3_coder_agent-0.1.1.dist-info/top_level.txt
qwen3_coder_agent-0.1.1.dist-info/RECORD
