Metadata-Version: 2.1
Name: qwen3-coder-agent
Version: 0.1.1
Summary: A terminal-based agent for interacting with Qwen3-Coder models
Home-page: https://github.com/yourusername/qwen3-coder-agent
Author: Your Name
Author-email: your.email@example.com
Project-URL: Bug Reports, https://github.com/yourusername/qwen3-coder-agent/issues
Project-URL: Source, https://github.com/yourusername/qwen3-coder-agent
Project-URL: Documentation, https://github.com/yourusername/qwen3-coder-agent#readme
Keywords: qwen3 coder ai assistant terminal cli code generation
Classifier: Development Status :: 3 - Alpha
Classifier: Intended Audience :: Developers
Classifier: License :: OSI Approved :: MIT License
Classifier: Operating System :: OS Independent
Classifier: Programming Language :: Python :: 3.8
Classifier: Programming Language :: Python :: 3.9
Classifier: Programming Language :: Python :: 3.10
Classifier: Programming Language :: Python :: 3.11
Classifier: Programming Language :: Python :: 3.12
Classifier: Topic :: Software Development
Classifier: Topic :: Terminals
Classifier: Typing :: Typed
Requires-Python: >=3.8
License-File: LICENSE
Requires-Dist: python-dotenv>=1.0.0
Requires-Dist: requests>=2.31.0
Requires-Dist: tiktoken>=0.4.0
Requires-Dist: pygments>=2.15.1
Requires-Dist: colorama>=0.4.6
Requires-Dist: prompt-toolkit>=3.0.38
Requires-Dist: tenacity>=8.2.2
Requires-Dist: pytest>=7.3.1
Requires-Dist: pytest-cov>=4.0.0
Requires-Dist: mypy>=1.3.0
Requires-Dist: black>=23.3.0
Requires-Dist: isort>=5.12.0
Requires-Dist: flake8>=6.0.0
Requires-Dist: pycodestyle>=2.12.0
Provides-Extra: dev
Requires-Dist: pytest>=7.3.1; extra == "dev"
Requires-Dist: pytest-cov>=4.0.0; extra == "dev"
Requires-Dist: mypy>=1.3.0; extra == "dev"
Requires-Dist: black>=23.3.0; extra == "dev"
Requires-Dist: isort>=5.12.0; extra == "dev"
Requires-Dist: flake8>=6.0.0; extra == "dev"
